Workbook
Name Cleaned_Product_Type: 'Cleaned-Sales Dataset'!$O$3:$O$100
Name Order_Priority: Europe_Sales_Records__2[[#All],[Order Priority]]
Name Product_Type: Europe_Sales_Records__2[[#All],[Product Type]]
Name Sales_Channel: Europe_Sales_Records__2[Sales Channel]

Sheet Raw-Sales Dataset
A1: Region | B1: Country | C1: Item Type | D1: Sales Channel | E1: Order Priority | F1: Order Date | G1: Order ID | H1: Ship Date | I1: Units Sold | J1: Unit Price | K1: Unit Cost | L1: Total Revenue | M1: Total Cost | N1: Total Profit
A2: Europe | B2: Czech Republic | C2: Beverages | D2: Offline | E2: C | F2: 9/12/2011 | G2: 478051030 | H2: 9/29/2011 | I2: 4778 | J2: 47.45 | K2: 31.79 | L2: 226716.1 | M2: 151892.62 | N2: 74823.48
A3: Europe | B3: Bosnia and Herzegovina | C3: Clothes | D3: Online | E3: M | F3: 10/14/2013 | G3: 919133651 | H3: 11/4/2013 | I3: 927 | J3: 109.28 | K3: 35.84 | L3: 101302.56 | M3: 33223.68 | N3: 68078.88
A4: Europe | B4: Austria | C4: Cereal | D4: Offline | E4: C | F4: 8/13/2014 | G4: 987410676 | H4: 9/6/2014 | I4: 5616 | J4: 205.7 | K4: 117.11 | L4: 1155211.2 | M4: 657689.76 | N4: 497521.44
A5: Europe | B5: Bulgaria | C5: Office Supplies | D5: Online | E5: L | F5: 10/31/2010 | G5: 672330081 | H5: 11/29/2010 | I5: 6266 | J5: 651.21 | K5: 524.96 | L5: 4080481.9 | M5: 3289399.4 | N5: 791082.5
A6: Europe | B6: Estonia | C6: Fruits | D6: Online | E6: L | F6: 9/28/2016 | G6: 579463422 | H6: 11/1/2016 | I6: 4958 | J6: 9.33 | K6: 6.92 | L6: 46258.14 | M6: 34309.36 | N6: 11948.78
A7: Europe | B7: Montenegro | C7: Fruits | D7: Offline | E7: L | F7: 5/29/2016 | G7: 313705861 | H7: 7/10/2016 | I7: 1390 | J7: 9.33 | K7: 6.92 | L7: 12968.7 | M7: 9618.8 | N7: 3349.9
A8: Europe | B8: Czech Republic | C8: Cereal | D8: Online | E8: M | F8: 7/8/2011 | G8: 552037513 | H8: 8/5/2011 | I8: 9022 | J8: 205.7 | K8: 117.11 | L8: 1855825.4 | M8: 1056566.4 | N8: 799258.98
A9: Europe | B9: Luxembourg | C9: Vegetables | D9: Offline | E9: L | F9: 2/13/2010 | G9: 744683635 | H9: 4/1/2010 | I9: 7291 | J9: 154.06 | K9: 90.93 | L9: 1123251.5 | M9: 662970.63 | N9: 460280.83
A10: Europe | B10: Switzerland | C10: Meat | D10: Online | E10: L | F10: 3/21/2014 | G10: 169378983 | H10: 4/10/2014 | I10: 1860 | J10: 421.89 | K10: 364.69 | L10: 784715.4 | M10: 678323.4 | N10: 106392
A11: Europe | B11: Finland | C11: Beverages | D11: Online | E11: H | F11: 3/16/2012 | G11: 566428315 | H11: 3/23/2012 | I11: 7581 | J11: 47.45 | K11: 31.79 | L11: 359718.45 | M11: 240999.99 | N11: 118718.46
A12: Europe | B12: Belgium | C12: Snacks | D12: Online | E12: M | F12: 1/12/2015 | G12: 519380223 | H12: 1/17/2015 | I12: 5005 | J12: 152.58 | K12: 97.44 | L12: 763662.9 | M12: 487687.2 | N12: 275975.7
A13: Europe | B13: San Marino | C13: Office Supplies | D13: Online | E13: H | F13: 4/13/2014 | G13: 904589211 | H13: 5/4/2014 | I13: 6905 | J13: 651.21 | K13: 524.96 | L13: 4496605 | M13: 3624848.8 | N13: 871756.25
... A200: Europe | B200: Latvia | C200: Beverages | D200: Online | E200: C | F200: 11/27/2013 | G200: 469197165 | H200: 12/11/2013 | I200: 4723 | J200: 47.45 | K200: 31.79 | L200: 224106.35 | M200: 150144.17 | N200: 73962.18

Sheet Cleaned-Sales Dataset
A1: Order ID | B1: Order Date | C1: Ship Date | D1: Region | E1: Country | F1: Product Type | G1: Sales Channel | H1: Order Priority | I1: Units Sold | J1: Unit Price | K1: Unit Cost | L1: Total Revenue | M1: Total Cost | N1: Total Profit | O1: Clean Product Type
A2: 298228013 | B2: 9/20/2010 | C2: 10/25/2010 | D2: Europe | E2: Sweden | F2: Vegetables | G2: Online | H2: High | I2: 1151 | J2: 154.06 | K2: 90.93 | L2: 177323.06 | M2: 104660.43 | N2: 72662.63 | O2: =TRIM(Europe_Sales_Records__2[[#This Row],[Product Type]]) -> Vegetables
A3: 697638976 | B3: 3/16/2015 | C3: 3/26/2015 | D3: Europe | E3: Serbia | F3: Vegetables | G3: Offline | H3: Low | I3: 5731 | J3: 154.06 | K3: 90.93 | L3: 882917.86 | M3: 521119.83 | N3: 361798.03 | O3: =TRIM(Europe_Sales_Records__2[[#This Row],[Product Type]]) -> Vegetables
A4: 810752236 | B4: 3/28/2016 | C4: 5/4/2016 | D4: Europe | E4: Moldova | F4: Vegetables | G4: Online | H4: Low | I4: 8458 | J4: 154.06 | K4: 90.93 | L4: 1303039.5 | M4: 769085.94 | N4: 533953.54 | O4: =TRIM(Europe_Sales_Records__2[[#This Row],[Product Type]]) -> Vegetables
A5: 743769109 | B5: 5/10/2016 | C5: 5/11/2016 | D5: Europe | E5: Malta | F5: Vegetables | G5: Online | H5: Medium | I5: 6662 | J5: 154.06 | K5: 90.93 | L5: 1026347.7 | M5: 605775.66 | N5: 420572.06 | O5: =TRIM(Europe_Sales_Records__2[[#This Row],[Product Type]]) -> Vegetables
A6: 894589078 | B6: 3/11/2014 | C6: 4/10/2014 | D6: Europe | E6: Malta | F6: Vegetables | G6: Online | H6: Medium | I6: 7643 | J6: 154.06 | K6: 90.93 | L6: 1177480.6 | M6: 694977.99 | N6: 482502.59 | O6: =TRIM(Europe_Sales_Records__2[[#This Row],[Product Type]]) -> Vegetables
A7: 744683635 | B7: 2/13/2010 | C7: 4/1/2010 | D7: Europe | E7: Luxembourg | F7: Vegetables | G7: Offline | H7: Low | I7: 7291 | J7: 154.06 | K7: 90.93 | L7: 1123251.5 | M7: 662970.63 | N7: 460280.83 | O7: =TRIM(Europe_Sales_Records__2[[#This Row],[Product Type]]) -> Vegetables
A8: 818976962 | B8: 12/18/2012 | C8: 12/21/2012 | D8: Europe | E8: Kosovo | F8: Vegetables | G8: Offline | H8: Critical | I8: 2337 | J8: 154.06 | K8: 90.93 | L8: 360038.22 | M8: 212503.41 | N8: 147534.81 | O8: =TRIM(Europe_Sales_Records__2[[#This Row],[Product Type]]) -> Vegetables
A9: 901670968 | B9: 11/16/2010 | C9: 12/11/2010 | D9: Europe | E9: Ireland | F9: Vegetables | G9: Offline | H9: Critical | I9: 3331 | J9: 154.06 | K9: 90.93 | L9: 513173.86 | M9: 302887.83 | N9: 210286.03 | O9: =TRIM(Europe_Sales_Records__2[[#This Row],[Product Type]]) -> Vegetables
A10: 204418504 | B10: 8/7/2015 | C10: 9/3/2015 | D10: Europe | E10: Germany | F10: Vegetables | G10: Offline | H10: Critical | I10: 833 | J10: 154.06 | K10: 90.93 | L10: 128331.98 | M10: 75744.69 | N10: 52587.29 | O10: =TRIM(Europe_Sales_Records__2[[#This Row],[Product Type]]) -> Vegetables
A11: 455040681 | B11: 2/1/2012 | C11: 2/2/2012 | D11: Europe | E11: France | F11: Vegetables | G11: Offline | H11: Low | I11: 5504 | J11: 154.06 | K11: 90.93 | L11: 847946.24 | M11: 500478.72 | N11: 347467.52 | O11: =TRIM(Europe_Sales_Records__2[[#This Row],[Product Type]]) -> Vegetables
A12: 771674382 | B12: 2/14/2013 | C12: 3/21/2013 | D12: Europe | E12: Finland | F12: Vegetables | G12: Offline | H12: Low | I12: 4453 | J12: 154.06 | K12: 90.93 | L12: 686029.18 | M12: 404911.29 | N12: 281117.89 | O12: =TRIM(Europe_Sales_Records__2[[#This Row],[Product Type]]) -> Vegetables
A13: 800352561 | B13: 9/28/2012 | C13: 10/21/2012 | D13: Europe | E13: Finland | F13: Vegetables | G13: Online | H13: High | I13: 963 | J13: 154.06 | K13: 90.93 | L13: 148359.78 | M13: 87565.59 | N13: 60794.19 | O13: =TRIM(Europe_Sales_Records__2[[#This Row],[Product Type]]) -> Vegetables
... A100: 990774810 | B100: 1/17/2014 | C100: 2/18/2014 | D100: Europe | E100: Netherlands | F100: Household | G100: Offline | H100: Critical | I100: 1138 | J100: 668.27 | K100: 502.54 | L100: 760491.26 | M100: 571890.52 | N100: 188600.74 | O100: =TRIM(Europe_Sales_Records__2[[#This Row],[Product Type]]) -> Household

Sheet Insights
A1: Sales Analysis Summary
B4: Country Revenue Summary | G4: Top 10 Countries by Revenue | K4: Orders by Product and Priority
B6: # | C6: Country | D6: Revenue | G6: # | H6: Country | I6: Revenue | M6: Order Priority
B7: 1 | C7: {=_xlfn.UNIQUE(Europe_Sales_Records__2[Country])} -> Sweden | D7: =SUMIF(Europe_Sales_Records__2[Country], Insights!$C7, Europe_Sales_Records__2[Total Revenue]) -> 177323.06 | G7: 1 | H7: {=_xlfn.TAKE(_xlfn._xlws.SORT(C7:D48,2,-1),10)} -> Portugal | I7: 9829878.2 | K7: # | L7: Product | M7: {=TRANSPOSE(_xlfn.UNIQUE(Europe_Sales_Records__2[Order Priority],FALSE))} -> High | N7: Low | O7: Medium | P7: Critical
B8: 2 | C8: Serbia | D8: =SUMIF(Europe_Sales_Records__2[Country], Insights!$C8, Europe_Sales_Records__2[Total Revenue]) -> 5079035.8 | G8: 2 | H8: Poland | I8: 9586346.3 | K8: 1 | L8: {=_xlfn.UNIQUE(Europe_Sales_Records__2[Product Type])} -> Vegetables | M8: {=COUNTIFS(Product_Type,Insights!$L8,Order_Priority,Insights!M$7)} -> 2 | N8: {=COUNTIFS(Product_Type,Insights!$L8,Order_Priority,Insights!N$7)} -> 6 | O8: {=COUNTIFS(Product_Type,Insights!$L8,Order_Priority,Insights!O$7)} -> 3 | P8: {=COUNTIFS(Product_Type,Insights!$L8,Order_Priority,Insights!P$7)} -> 6
B9: 3 | C9: Moldova | D9: =SUMIF(Europe_Sales_Records__2[Country], Insights!$C9, Europe_Sales_Records__2[Total Revenue]) -> 3797554.8 | G9: 3 | H9: Bulgaria | I9: 8700690.4 | K9: 2 | L9: Snacks | M9: {=COUNTIFS(Product_Type,Insights!$L9,Order_Priority,Insights!M$7)} -> 6 | N9: {=COUNTIFS(Product_Type,Insights!$L9,Order_Priority,Insights!N$7)} -> 6 | O9: {=COUNTIFS(Product_Type,Insights!$L9,Order_Priority,Insights!O$7)} -> 2 | P9: {=COUNTIFS(Product_Type,Insights!$L9,Order_Priority,Insights!P$7)} -> 3
B10: 4 | C10: Malta | D10: =SUMIF(Europe_Sales_Records__2[Country], Insights!$C10, Europe_Sales_Records__2[Total Revenue]) -> 2626862.8 | G10: 4 | H10: Bosnia and Herzegovina | I10: 7947356.6 | K10: 3 | L10: Personal Care | M10: {=COUNTIFS(Product_Type,Insights!$L10,Order_Priority,Insights!M$7)} -> 6 | N10: {=COUNTIFS(Product_Type,Insights!$L10,Order_Priority,Insights!N$7)} -> 7 | O10: {=COUNTIFS(Product_Type,Insights!$L10,Order_Priority,Insights!O$7)} -> 8 | P10: {=COUNTIFS(Product_Type,Insights!$L10,Order_Priority,Insights!P$7)} -> 2
B11: 5 | C11: Luxembourg | D11: =SUMIF(Europe_Sales_Records__2[Country], Insights!$C11, Europe_Sales_Records__2[Total Revenue]) -> 1623866.4 | G11: 5 | H11: Italy | I11: 7674961.7 | K11: 4 | L11: Office Supplies | M11: {=COUNTIFS(Product_Type,Insights!$L11,Order_Priority,Insights!M$7)} -> 7 | N11: {=COUNTIFS(Product_Type,Insights!$L11,Order_Priority,Insights!N$7)} -> 3 | O11: {=COUNTIFS(Product_Type,Insights!$L11,Order_Priority,Insights!O$7)} -> 2 | P11: {=COUNTIFS(Product_Type,Insights!$L11,Order_Priority,Insights!P$7)} -> 6
B12: 6 | C12: Kosovo | D12: =SUMIF(Europe_Sales_Records__2[Country], Insights!$C12, Europe_Sales_Records__2[Total Revenue]) -> 3665651.8 | G12: 6 | H12: Russia | I12: 6876714.1 | K12: 5 | L12: Meat | M12: {=COUNTIFS(Product_Type,Insights!$L12,Order_Priority,Insights!M$7)} -> 6 | N12: {=COUNTIFS(Product_Type,Insights!$L12,Order_Priority,Insights!N$7)} -> 5 | O12: {=COUNTIFS(Product_Type,Insights!$L12,Order_Priority,Insights!O$7)} -> 3 | P12: {=COUNTIFS(Product_Type,Insights!$L12,Order_Priority,Insights!P$7)} -> 3
B13: 7 | C13: Ireland | D13: =SUMIF(Europe_Sales_Records__2[Country], Insights!$C13, Europe_Sales_Records__2[Total Revenue]) -> 595802.89 | G13: 7 | H13: San Marino | I13: 5458164.2 | K13: 6 | L13: Household | M13: {=COUNTIFS(Product_Type,Insights!$L13,Order_Priority,Insights!M$7)} -> 0 | N13: {=COUNTIFS(Product_Type,Insights!$L13,Order_Priority,Insights!N$7)} -> 3 | O13: {=COUNTIFS(Product_Type,Insights!$L13,Order_Priority,Insights!O$7)} -> 2 | P13: {=COUNTIFS(Product_Type,Insights!$L13,Order_Priority,Insights!P$7)} -> 2
B14: 8 | C14: Germany | D14: =SUMIF(Europe_Sales_Records__2[Country], Insights!$C14, Europe_Sales_Records__2[Total Revenue]) -> 1567758.3 | G14: 8 | H14: Serbia | I14: 5079035.8
B15: 9 | C15: France | D15: =SUMIF(Europe_Sales_Records__2[Country], Insights!$C15, Europe_Sales_Records__2[Total Revenue]) -> 956371.97 | G15: 9 | H15: Slovenia | I15: 4672543.8
B16: 10 | C16: Finland | D16: =SUMIF(Europe_Sales_Records__2[Country], Insights!$C16, Europe_Sales_Records__2[Total Revenue]) -> 4221332.2 | G16: 10 | H16: Latvia | I16: 4633762.7
B17: 11 | C17: Cyprus | D17: =SUMIF(Europe_Sales_Records__2[Country], Insights!$C17, Europe_Sales_Records__2[Total Revenue]) -> 1472505.5
B18: 12 | C18: Belgium | D18: =SUMIF(Europe_Sales_Records__2[Country], Insights!$C18, Europe_Sales_Records__2[Total Revenue]) -> 1532114.2
B19: 13 | C19: Belarus | D19: =SUMIF(Europe_Sales_Records__2[Country], Insights!$C19, Europe_Sales_Records__2[Total Revenue]) -> 2682298.4
B20: 14 | C20: Armenia | D20: =SUMIF(Europe_Sales_Records__2[Country], Insights!$C20, Europe_Sales_Records__2[Total Revenue]) -> 3158023.3 | G20: Total Profit by Product | K20: Order by Products and Sales Channel
B21: 15 | C21: Albania | D21: =SUMIF(Europe_Sales_Records__2[Country], Insights!$C21, Europe_Sales_Records__2[Total Revenue]) -> 1643231.5 | M21: Sales Channel
B22: 16 | C22: United Kingdom | D22: =SUMIF(Europe_Sales_Records__2[Country], Insights!$C22, Europe_Sales_Records__2[Total Revenue]) -> 1175989.4 | G22: # | H22: Product | I22: Profit | K22: # | L22: Product | M22: {=TRANSPOSE(_xlfn.UNIQUE(Europe_Sales_Records__2[Sales Channel]))} -> Online | N22: Offline
B23: 17 | C23: Ukraine | D23: =SUMIF(Europe_Sales_Records__2[Country], Insights!$C23, Europe_Sales_Records__2[Total Revenue]) -> 1034775.9 | G23: 1 | H23: {=_xlfn.UNIQUE(Europe_Sales_Records__2[Product Type])} -> Vegetables | I23: =SUMIF(Europe_Sales_Records__2[Product Type], Insights!$H23, Europe_Sales_Records__2[Total Profit]) -> 5580439.5 | K23: 1 | L23: {=_xlfn.UNIQUE(Europe_Sales_Records__2[Product Type])} -> Vegetables | M23: {=COUNTIFS(Europe_Sales_Records__2[Clean Product Type],$L23,Sales_Channel,M$22)} -> 8 | N23: {=COUNTIFS(Europe_Sales_Records__2[Clean Product Type],$L23,Sales_Channel,N$22)} -> 9
B24: 18 | C24: Slovakia | D24: =SUMIF(Europe_Sales_Records__2[Country], Insights!$C24, Europe_Sales_Records__2[Total Revenue]) -> 1102632 | G24: 2 | H24: Snacks | I24: =SUMIF(Europe_Sales_Records__2[Product Type], Insights!$H24, Europe_Sales_Records__2[Total Profit]) -> 4007023.8 | K24: 2 | L24: Snacks | M24: {=COUNTIFS(Europe_Sales_Records__2[Clean Product Type],$L24,Sales_Channel,M$22)} -> 11 | N24: {=COUNTIFS(Europe_Sales_Records__2[Clean Product Type],$L24,Sales_Channel,N$22)} -> 6
B25: 19 | C25: San Marino | D25: =SUMIF(Europe_Sales_Records__2[Country], Insights!$C25, Europe_Sales_Records__2[Total Revenue]) -> 5458164.2 | G25: 3 | H25: Personal Care | I25: =SUMIF(Europe_Sales_Records__2[Product Type], Insights!$H25, Europe_Sales_Records__2[Total Profit]) -> 2789954.9 | K25: 3 | L25: Personal Care | M25: {=COUNTIFS(Europe_Sales_Records__2[Clean Product Type],$L25,Sales_Channel,M$22)} -> 11 | N25: {=COUNTIFS(Europe_Sales_Records__2[Clean Product Type],$L25,Sales_Channel,N$22)} -> 12
B26: 20 | C26: Romania | D26: =SUMIF(Europe_Sales_Records__2[Country], Insights!$C26, Europe_Sales_Records__2[Total Revenue]) -> 1572200.8 | G26: 4 | H26: Office Supplies | I26: =SUMIF(Europe_Sales_Records__2[Product Type], Insights!$H26, Europe_Sales_Records__2[Total Profit]) -> 9527582.5 | K26: 4 | L26: Office Supplies | M26: {=COUNTIFS(Europe_Sales_Records__2[Clean Product Type],$L26,Sales_Channel,M$22)} -> 8 | N26: {=COUNTIFS(Europe_Sales_Records__2[Clean Product Type],$L26,Sales_Channel,N$22)} -> 10
B27: 21 | C27: Latvia | D27: =SUMIF(Europe_Sales_Records__2[Country], Insights!$C27, Europe_Sales_Records__2[Total Revenue]) -> 4633762.7 | G27: 5 | H27: Meat | I27: =SUMIF(Europe_Sales_Records__2[Product Type], Insights!$H27, Europe_Sales_Records__2[Total Profit]) -> 4496949.6 | K27: 5 | L27: Meat | M27: {=COUNTIFS(Europe_Sales_Records__2[Clean Product Type],$L27,Sales_Channel,M$22)} -> 8 | N27: {=COUNTIFS(Europe_Sales_Records__2[Clean Product Type],$L27,Sales_Channel,N$22)} -> 9
B28: 22 | C28: Italy | D28: =SUMIF(Europe_Sales_Records__2[Country], Insights!$C28, Europe_Sales_Records__2[Total Revenue]) -> 7674961.7 | G28: 6 | H28: Household | I28: =SUMIF(Europe_Sales_Records__2[Product Type], Insights!$H28, Europe_Sales_Records__2[Total Profit]) -> 2142060.2 | K28: 6 | L28: Household | M28: {=COUNTIFS(Europe_Sales_Records__2[Clean Product Type],$L28,Sales_Channel,M$22)} -> 2 | N28: {=COUNTIFS(Europe_Sales_Records__2[Clean Product Type],$L28,Sales_Channel,N$22)} -> 5
B29: 23 | C29: Iceland | D29: =SUMIF(Europe_Sales_Records__2[Country], Insights!$C29, Europe_Sales_Records__2[Total Revenue]) -> 1287927.8
B30: 24 | C30: Bulgaria | D30: =SUMIF(Europe_Sales_Records__2[Country], Insights!$C30, Europe_Sales_Records__2[Total Revenue]) -> 8700690.4
B31: 25 | C31: Andorra | D31: =SUMIF(Europe_Sales_Records__2[Country], Insights!$C31, Europe_Sales_Records__2[Total Revenue]) -> 3292737.5
B32: 26 | C32: Russia | D32: =SUMIF(Europe_Sales_Records__2[Country], Insights!$C32, Europe_Sales_Records__2[Total Revenue]) -> 6876714.1
B33: 27 | C33: Poland | D33: =SUMIF(Europe_Sales_Records__2[Country], Insights!$C33, Europe_Sales_Records__2[Total Revenue]) -> 9586346.3
B34: 28 | C34: Norway | D34: =SUMIF(Europe_Sales_Records__2[Country], Insights!$C34, Europe_Sales_Records__2[Total Revenue]) -> 1513705.6
B35: 29 | C35: Monaco | D35: =SUMIF(Europe_Sales_Records__2[Country], Insights!$C35, Europe_Sales_Records__2[Total Revenue]) -> 511548.07
B36: 30 | C36: Macedonia | D36: =SUMIF(Europe_Sales_Records__2[Country], Insights!$C36, Europe_Sales_Records__2[Total Revenue]) -> 530345.97
B37: 31 | C37: Lithuania | D37: =SUMIF(Europe_Sales_Records__2[Country], Insights!$C37, Europe_Sales_Records__2[Total Revenue]) -> 1391149.7
B38: 32 | C38: Greece | D38: =SUMIF(Europe_Sales_Records__2[Country], Insights!$C38, Europe_Sales_Records__2[Total Revenue]) -> 718161.51
B39: 33 | C39: Czech Republic | D39: =SUMIF(Europe_Sales_Records__2[Country], Insights!$C39, Europe_Sales_Records__2[Total Revenue]) -> 190757.82
B40: 34 | C40: Bosnia and Herzegovina | D40: =SUMIF(Europe_Sales_Records__2[Country], Insights!$C40, Europe_Sales_Records__2[Total Revenue]) -> 7947356.6
... B47: 41 | C47: Slovenia | D47: =SUMIF(Europe_Sales_Records__2[Country], Insights!$C47, Europe_Sales_Records__2[Total Revenue]) -> 4672543.8
